gitflux/__init__.py
gitflux/__main__.py
gitflux/commands/__init__.py
gitflux/commands/create_repos.py
gitflux/commands/delete_repos.py
gitflux/commands/list_repos.py
gitflux/providers/__init__.py
gitflux/providers/gitee.py
gitflux/providers/github.py
gitflux/typing.py
gitflux-1.1.0.dist-info/COPYING
gitflux-1.1.0.dist-info/METADATA
gitflux-1.1.0.dist-info/WHEEL
gitflux-1.1.0.dist-info/entry_points.txt
gitflux-1.1.0.dist-info/RECORD
