Metadata-Version: 2.1
Name: gitflux
Version: 1.1.0
Summary: A nested command-line utility that helps you manage repositories hosted on Git service providers.
License: GPL-3.0
Author: HE Yaowen
Author-email: he.yaowen@hotmail.com
Requires-Python: >=3.7.2,<3.12
Classifier: License :: OSI Approved :: GNU General Public License v3 (GPLv3)
Classifier: Programming Language :: Python :: 3
Classifier: Programming Language :: Python :: 3.8
Classifier: Programming Language :: Python :: 3.9
Classifier: Programming Language :: Python :: 3.10
Classifier: Programming Language :: Python :: 3.11
Requires-Dist: click (>=8.1.3,<9.0.0)
Requires-Dist: pygithub (>=1.55,<2.0)
